mtmlpkg/__init__.py
mtmlpkg/mtml.py
pymtml-0.0.3.dist-info/METADATA
pymtml-0.0.3.dist-info/WHEEL
pymtml-0.0.3.dist-info/top_level.txt
pymtml-0.0.3.dist-info/RECORD
