Metadata-Version: 2.4
Name: pymtml
Version: 0.0.3
Summary: A simple demo Python package for PyPI
Home-page: https://github.com/yourname/hellopkg
Author: zhouyu
Author-email: zhouyuzf@163.com
License: MIT
Classifier: Programming Language :: Python :: 3
Classifier: License :: OSI Approved :: MIT License
Classifier: Operating System :: OS Independent
Requires-Python: >=3.7
Dynamic: author
Dynamic: author-email
Dynamic: classifier
Dynamic: description
Dynamic: description-content-type
Dynamic: home-page
Dynamic: license
Dynamic: requires-python
Dynamic: summary
